fastapi_healthz/__init__.py
fastapi_healthz/models.py
fastapi_healthz/registry.py
fastapi_healthz/route.py
fastapi_healthz/service/__init__.py
fastapi_healthz/service/abstract.py
fastapi_healthz/service/database_check.py
fastapi_healthz/service/mongodb_check.py
fastapi_healthz/service/rabbitmq_check.py
fastapi_healthz/service/redis_check.py
fastapi_healthz/service/s3_check.py
fastapi_healthz/service/uri_check.py
fastapi_healthz/utils.py
fastapi_healthz-1.3.3.dist-info/LICENSE
fastapi_healthz-1.3.3.dist-info/METADATA
fastapi_healthz-1.3.3.dist-info/WHEEL
fastapi_healthz-1.3.3.dist-info/RECORD
