Metadata-Version: 2.3
Name: fastapi-healthz
Version: 1.3.3
Summary: A module to have a FastAPI HealthCheck for database, RabbitMQ server, Redis, MongoDB or external URI to validate their healths.
License: MIT
Author: Matteo Cacciola
Author-email: matteo.cacciola@gmail.com
Requires-Python: >=3.10,<4.0
Classifier: Development Status :: 5 - Production/Stable
Classifier: Framework :: FastAPI
Classifier: License :: OSI Approved :: MIT License
Classifier: Programming Language :: Python :: 3
Classifier: Programming Language :: Python :: 3.10
Classifier: Programming Language :: Python :: 3.11
Classifier: Programming Language :: Python :: 3.12
Classifier: Programming Language :: Python :: 3.13
Provides-Extra: all
Provides-Extra: database
Provides-Extra: mongodb
Provides-Extra: rabbitmq
Provides-Extra: redis
Provides-Extra: s3
Provides-Extra: uri
Requires-Dist: boto3 (>=1.40.61,<2.0.0) ; extra == "s3" or extra == "all"
Requires-Dist: fastapi (>=0.116.1,<0.117.0) ; extra == "rabbitmq" or extra == "redis" or extra == "database" or extra == "mongodb" or extra == "uri" or extra == "s3" or extra == "all"
Requires-Dist: pika (>=1.3.2,<2.0.0) ; extra == "rabbitmq" or extra == "all"
Requires-Dist: pydantic (>=2.11.7,<3.0.0) ; extra == "rabbitmq" or extra == "redis" or extra == "database" or extra == "mongodb" or extra == "uri" or extra == "s3" or extra == "all"
Requires-Dist: pymongo (>=4.9.1,<5.0.0) ; extra == "mongodb" or extra == "all"
Requires-Dist: redis (>=6.4.0,<7.0.0) ; extra == "redis" or extra == "all"
Requires-Dist: requests (>=2.32.5,<3.0.0) ; extra == "rabbitmq" or extra == "redis" or extra == "database" or extra == "mongodb" or extra == "uri" or extra == "s3" or extra == "all"
Requires-Dist: sqlalchemy (>=2.0.43,<3.0.0) ; extra == "database" or extra == "all"
Project-URL: Repository, https://github.com/matteocacciola/fastapi_healthz
